{
  "routeKey": "doingapi.POST._actions",
  "parameters": [],
  "requestBody": {
    "required": true,
    "content": {
      "application/json": {
        "schema": {
          "type": "array",
          "items": {
            "$ref": "#/components/schemas/Action"
          }
        }
      }
    }
  },
  "responses": {
    "200": {
      "description": "Successful response",
      "content": {
        "application/json": {
          "schema": {
            "type": "array",
            "items": {
              "$ref": "#/components/schemas/Action"
            }
          }
        }
      }
    }
  },
  "security": [],
  "examples": []
}